geometric_algebra_attention/__init__.py
geometric_algebra_attention/version.py
geometric_algebra_attention/base/LabeledMultivectorAttention.py
geometric_algebra_attention/base/LabeledVectorAttention.py
geometric_algebra_attention/base/Multivector2MultivectorAttention.py
geometric_algebra_attention/base/Multivector2Vector.py
geometric_algebra_attention/base/MultivectorAttention.py
geometric_algebra_attention/base/TiedMultivectorAttention.py
geometric_algebra_attention/base/TiedVectorAttention.py
geometric_algebra_attention/base/Vector2Multivector.py
geometric_algebra_attention/base/Vector2VectorAttention.py
geometric_algebra_attention/base/VectorAttention.py
geometric_algebra_attention/base/__init__.py
geometric_algebra_attention/base/internal.py
geometric_algebra_attention/jax/LabeledMultivectorAttention.py
geometric_algebra_attention/jax/LabeledVectorAttention.py
geometric_algebra_attention/jax/Multivector2MultivectorAttention.py
geometric_algebra_attention/jax/Multivector2Vector.py
geometric_algebra_attention/jax/MultivectorAttention.py
geometric_algebra_attention/jax/TiedMultivectorAttention.py
geometric_algebra_attention/jax/TiedVectorAttention.py
geometric_algebra_attention/jax/Vector2Multivector.py
geometric_algebra_attention/jax/Vector2VectorAttention.py
geometric_algebra_attention/jax/VectorAttention.py
geometric_algebra_attention/jax/__init__.py
geometric_algebra_attention/jax/geometric_algebra.py
geometric_algebra_attention/jax/internal.py
geometric_algebra_attention/keras/LabeledMultivectorAttention.py
geometric_algebra_attention/keras/LabeledVectorAttention.py
geometric_algebra_attention/keras/MomentumLayerNormalization.py
geometric_algebra_attention/keras/MomentumNormalization.py
geometric_algebra_attention/keras/Multivector2MultivectorAttention.py
geometric_algebra_attention/keras/Multivector2Vector.py
geometric_algebra_attention/keras/MultivectorAttention.py
geometric_algebra_attention/keras/TiedMultivectorAttention.py
geometric_algebra_attention-0.5.1.dist-info/LICENSE
geometric_algebra_attention-0.5.1.dist-info/METADATA
geometric_algebra_attention-0.5.1.dist-info/WHEEL
geometric_algebra_attention-0.5.1.dist-info/top_level.txt
geometric_algebra_attention-0.5.1.dist-info/RECORD
