Metadata-Version: 2.1
Name: geometric-algebra-attention
Version: 0.5.1
Summary: Library for geometric algebra-based attention mechanisms
Author: Matthew Spellings
Author-email: matthew.p.spellings@gmail.com
License: MIT
Project-URL: Documentation, http://geometric_algebra_attention.readthedocs.io/
Project-URL: Source, https://github.com/klarh/geometric_algebra_attention
Classifier: Development Status :: 3 - Alpha
Classifier: License :: OSI Approved :: MIT License
Classifier: Programming Language :: Python :: 3
Requires-Python: >=3
License-File: LICENSE
